{
	"configurations" : 
	[
		{
			"directories" : 
			[
				{
					"build" : ".",
					"jsonFile" : "directory-.-Debug-d0094a50bb2071803777.json",
					"minimumCMakeVersion" : 
					{
						"string" : "3.24"
					},
					"projectIndex" : 0,
					"source" : ".",
					"targetIndexes" : 
					[
						0
					]
				}
			],
			"name" : "Debug",
			"projects" : 
			[
				{
					"directoryIndexes" : 
					[
						0
					],
					"name" : "B2012_H1N1_mortality_rate",
					"targetIndexes" : 
					[
						0
					]
				}
			],
			"targets" : 
			[
				{
					"directoryIndex" : 0,
					"id" : "B2012_H1N1_mortality_rate::@6890427a1f51a3e7e1df",
					"jsonFile" : "target-B2012_H1N1_mortality_rate-Debug-1b7d3c73d39ffedd12ef.json",
					"name" : "B2012_H1N1_mortality_rate",
					"projectIndex" : 0
				}
			]
		}
	],
	"kind" : "codemodel",
	"paths" : 
	{
		"build" : "D:/C++ codes/Algorithm/B2012_H1N1_mortality_rate/cmake-build-debug",
		"source" : "D:/C++ codes/Algorithm/B2012_H1N1_mortality_rate"
	},
	"version" : 
	{
		"major" : 2,
		"minor" : 4
	}
}
